pypoolcontroller/__init__.py
pypoolcontroller-1.0.dist-info/LICENSE
pypoolcontroller-1.0.dist-info/METADATA
pypoolcontroller-1.0.dist-info/WHEEL
pypoolcontroller-1.0.dist-info/top_level.txt
pypoolcontroller-1.0.dist-info/RECORD
