Metadata-Version: 2.1
Name: pypoolcontroller
Version: 1.0
Summary: A python poolcontroller client
Home-page: https://github.com/leftyfl1p/pypoolcontroller
Author: leftyfl1p
Author-email: leftyfl1p@me.com
License: UNKNOWN
Platform: UNKNOWN
Classifier: Programming Language :: Python :: 3
Classifier: License :: OSI Approved :: MIT License
Classifier: Operating System :: OS Independent
Requires-Dist: aiohttp (>=3.5.4)
Requires-Dist: async-timeout (>=3.0.1)
